misc_date_utilities/__init__.py
misc_date_utilities/date_difference.py
misc_date_utilities/random_timestamp.py
misc_date_utilities/simple_parse.py
misc_date_utilities/tests/__init__.py
misc_date_utilities/tests/test_date_subtractor.py
misc_date_utilities-1.0.7.dist-info/LICENSE
misc_date_utilities-1.0.7.dist-info/METADATA
misc_date_utilities-1.0.7.dist-info/WHEEL
misc_date_utilities-1.0.7.dist-info/top_level.txt
misc_date_utilities-1.0.7.dist-info/RECORD
