Metadata-Version: 2.1
Name: misc-date-utilities
Version: 1.0.7
Summary: Date subtraction, parsing, and random timestamp generation.
Home-page: https://github.com/ktraw2/misc-date-utilities
Author: Kevin Traw
Author-email: ktraw2@gmail.com
License: UNKNOWN
Platform: UNKNOWN
Classifier: Programming Language :: Python :: 3
Classifier: Operating System :: OS Independent
Requires-Dist: dateutil
